<?xml version="1.0"?>
<database version="0.2" name="Horse">

    <!-- 3D model -->
    <model>
      <file>:/assets/models/horse/horse.obj</file>
    </model>

    <!--List of points-->
    <points>
        <point id="BI1">
            <tags>
                <tag name="Head"/>
                <tag name="Snout"/>
            </tags>
            <position x="128.902" y="179.277" z="30.43"/>
            <description>Pain in left ear; Nervus nervoesus</description>
            <color>#0000ff</color>
        </point>
        <point id="BI2">
            <tags>
                <tag name="Head"/>
                <tag name="Snout"/>
            </tags>
            <position x="128.902" y="179.277" z="30.43"/>
            <description>Pain in right ear</description>
            <color>#0000ff</color>
        </point>
        <point id="BI3">
            <tags>
                <tag name="Head"/>
                <tag name="Snout"/>
            </tags>
            <position x="128.902" y="179.277" z="30.43"/>
            <description>Mystic soul healing point</description>
            <color>#0000ff</color>
        </point>
        <point id="BI4">
            <tags>
                <tag name="Head"/>
                <tag name="Snout"/>
            </tags>
            <position x="128.902" y="179.277" z="30.43"/>
            <description>Don't know what this point does</description>
            <color>#0000ff</color>
        </point>
        <point id="BI5">
            <tags>
                <tag name="Head"/>
                <tag name="Snout"/>
            </tags>
            <position x="128.902" y="179.277" z="30.43"/>
            <description>North point</description>
            <color>#0000ff</color>
        </point>
        <point id="BI6">
            <tags>
                <tag name="Head"/>
                <tag name="Snout"/>
            </tags>
            <position x="128.902" y="179.277" z="30.43"/>
            <description>Accelerate horse</description>
            <color>#ff00ff</color>
        </point>
        <point id="BI7">
            <tags>
                <tag name="Head"/>
                <tag name="Snout"/>
            </tags>
            <position x="128.902" y="179.277" z="30.43"/>
            <description>Ouch ! That hurt !</description>
            <color>#ff00ff</color>
        </point>
        <point id="BI8">
            <tags>
                <tag name="Head"/>
                <tag name="Snout"/>
            </tags>
            <position x="128.902" y="179.277" z="30.43"/>
            <description>Apply with care</description>
            <color>#ff00ff</color>
        </point>
        <point id="BI9">
            <tags>
                <tag name="Head"/>
                <tag name="Snout"/>
            </tags>
            <position x="128.902" y="179.277" z="30.43"/>
            <description>Point of no return</description>
            <color>#ff00ff</color>
        </point>
        <point id="BI10">
            <tags>
                <tag name="Head"/>
                <tag name="Snout"/>
            </tags>
            <position x="128.902" y="179.277" z="30.43"/>
            <description>Mystic soul healing point</description>
            <color>#ff00ff</color>
        </point>
        <point id="BI11">
            <tags>
                <tag name="Head"/>
                <tag name="Snout"/>
            </tags>
            <position x="128.902" y="179.277" z="30.43"/>
            <description>Applying a needle here will color tail green</description>
            <color>#ff00ff</color>
        </point>
        <point id="BI12">
            <tags>
                <tag name="Head"/>
                <tag name="Snout"/>
            </tags>
            <position x="128.902" y="179.277" z="30.43"/>
            <description>Stomach connection</description>
            <color>#ff00ff</color>
        </point>
        <point id="CI1">
            <tags>
                <tag name="Back"/>
            </tags>
            <position x="128.902" y="179.277" z="30.43"/>
            <description>Do not touch this point, horse will explode !</description>
            <color>#008000</color>
        </point>
        <point id="CI2">
            <tags>
                <tag name="Back"/>
            </tags>
            <position x="128.902" y="179.277" z="30.43"/>
            <description>Horse gear shift</description>
            <color>#ff0000</color>
        </point>
        <point id="CI3">
            <tags>
                <tag name="Back"/>
            </tags>
            <position x="128.902" y="179.277" z="30.43"/>
            <description>Horse USB port</description>
            <color>#ff0000</color>
        </point>
        <point id="CI4">
            <tags>
                <tag name="Back"/>
            </tags>
            <position x="128.902" y="179.277" z="30.43"/>
            <description>Related to points BI2 and BI4</description>
            <color>#ff0000</color>
        </point>
        <point id="CI5">
            <tags>
                <tag name="Back"/>
            </tags>
            <position x="128.902" y="179.277" z="30.43"/>
            <description>The chinese would use this point</description>
            <color>#ff0000</color>
        </point>
        <point id="CI6">
            <tags>
                <tag name="Back"/>
            </tags>
            <position x="128.902" y="179.277" z="30.43"/>
            <description>Horse gear shift</description>
            <color>#ff0000</color>
        </point>
        <point id="CI7">
            <tags>
                <tag name="Back"/>
            </tags>
            <position x="128.902" y="179.277" z="30.43"/>
            <description>Horse left turn signal flasher</description>
            <color>#ff0000</color>
        </point>
        <point id="CI8">
            <tags>
                <tag name="Back"/>
            </tags>
            <position x="128.902" y="179.277" z="30.43"/>
            <description>Horse right turn signal flashes</description>
            <color>#ff0000</color>
        </point>
        <point id="DI1">
            <tags>
                <tag name="Spine"/>
            </tags>
            <position x="128.902" y="179.277" z="30.43"/>
            <description>Flip horse</description>
            <color>#00ff00</color>
        </point>
        <point id="DI2">
            <tags>
                <tag name="Spine"/>
            </tags>
            <position x="128.902" y="179.277" z="30.43"/>
            <description>Main spine connection</description>
            <color>#00ff00</color>
        </point>
        <point id="DI3">
            <tags>
                <tag name="Spine"/>
            </tags>
            <position x="128.902" y="179.277" z="30.43"/>
            <description>Connected to front left leg</description>
            <color>#00ff00</color>
        </point>
        <point id="XP1">
            <tags>
                <tag name="Abdomen"/>
            </tags>
            <position x="128.902" y="179.277" z="30.43"/>
            <description>Horse will empty bowel. Step back first.</description>
            <color>#00ffff</color>
        </point>
        <point id="XP2">
            <tags>
                <tag name="Abdomen"/>
            </tags>
            <position x="128.902" y="179.277" z="30.43"/>
            <description>Tickling here will make horse laughing.</description>
            <color>#00ffff</color>
        </point>
        <point id="XP3">
            <tags>
                <tag name="Abdomen"/>
            </tags>
            <position x="128.902" y="179.277" z="30.43"/>
            <description>Honestly, we do not now what this point does.</description>
            <color>#00ffff</color>
        </point>
        <point id="XP4">
            <tags>
                <tag name="Abdomen"/>
            </tags>
            <position x="128.902" y="179.277" z="30.43"/>
            <description>Point blank</description>
            <color>#00ffff</color>
        </point>
    </points>

</database>
